[
  {
    "university_id": "01",
    "university_name_th": "มหาวิทยาลัยมหิดล (ศาลายา)",
    "faculty": [
      {
        "faculty_id": "01",
        "faculty_name_th": "คณะเภสัชศาสตร์"
      },
      {
        "faculty_id": "02",
        "faculty_name_th": "คณะวิศวกรรมศาสตร์"
      }
    ],
    "course": [
      {
        "course_id": "01",
        "faculty_id": "01",
        "branch_name_th": "เภสัชศาสตรบัณฑิต",
        "graduated": {
          "core": true,
          "international": false,
          "vocation": false,
          "non_formol": false
        },
        "require_scores": {
          "TGAT": 25,
          "A_LEVEL_PHYSICS": 30,
          "A_LEVEL_CHEMICAL": 30,
          "A_LEVEL_BIOLOGY": 30,
          "A_LEVEL_ENGLISH": 30,
          "A_LEVEL_MATH_1": 30
        },
        "require_credit": {},
        "calulate_scores": {
          "TGAT": 20,
          "A_LEVEL_PHYSICS": 13,
          "A_LEVEL_CHEMICAL": 14,
          "A_LEVEL_BIOLOGY": 13,
          "A_LEVEL_ENGLISH": 20,
          "A_LEVEL_MATH_1": 20
        }
      },
      {
        "course_id": "02",
        "faculty_id": "01",
        "branch_name_th": "เทคนิคการแพทย์",
        "graduated": {
          "core": true,
          "international": false,
          "vocation": false,
          "non_formol": false
        },
        "require_scores": {
          "gpax": 2.5,
          "TGAT": 20,
          "TPAT3": 20,
          "A_LEVEL_CHEMICAL": 20,
          "A_LEVEL_BIOLOGY": 20,
          "A_LEVEL_ENGLISH": 20,
          "A_LEVEL_MATH_1": 20
        },
        "require_credit": {},
        "calulate_scores": {
          "TGAT": 20,
          "A_LEVEL_MATH_1": 10,
          "A_LEVEL_CHEMICAL": 30,
          "A_LEVEL_BIOLOGY": 30,
          "A_LEVEL_ENGLISH": 10
        }
      },
      {
        "course_id": "03",
        "faculty_id": "01",
        "branch_name_th": "พยาบาลศาสตรบัณทิต",
        "graduated": {
          "core": true,
          "international": false,
          "vocation": false,
          "non_formol": false
        },
        "require_scores": {
          "gpax": 2.75,
          "A_LEVEL_PHYSICS": 15,
          "A_LEVEL_CHEMICAL": 15,
          "A_LEVEL_BIOLOGY": 20,
          "A_LEVEL_THAI": 20,
          "A_LEVEL_ENGLISH": 25,
          "A_LEVEL_MATH_1": 15,
          "A_LEVEL_SOCIAL": 20
        },
        "require_credit": {},
        "calulate_scores": {
          "TGAT": 30,
          "A_LEVEL_MATH_1": 25,
          "A_LEVEL_BIOLOGY": 10,
          "A_LEVEL_CHEMICAL": 10,
          "A_LEVEL_ENGLISH": 25
        }
      },
      {
        "course_id": "04",
        "faculty_id": "02",
        "branch_name_th": "วิศวกรรมคอมพิวเตอร์",
        "graduated": {
          "core": true,
          "international": true,
          "vocation": false,
          "non_formol": false
        },
        "require_scores": {
          "gpax": 3.0
        },
        "require_credit": {},
        "calulate_scores": {
          "TPAT3": 30,
          "A_LEVEL_MATH_1": 25,
          "A_LEVEL_PHYSICS": 25,
          "A_LEVEL_ENGLISH": 20
        }
      },
      {
        "course_id": "05",
        "faculty_id": "02",
        "branch_name_th": "วิศวกรรมเครื่องกล",
        "graduated": {
          "core": true,
          "international": true,
          "vocation": false,
          "non_formol": false
        },
        "require_scores": {
          "gpax": 3.0
        },
        "require_credit": {},
        "calulate_scores": {
          "TGAT": 20,
          "TPAT3": 30,
          "A_LEVEL_MATH_1": 25,
          "A_LEVEL_PHYSICS": 25
        }
      }
      
    ]
  }
]